{
  "event_id": "2026_spa_3h_endurance",
  "event_name": "The SRCS Spa 3-hour Endurance",
  "banner_image": "assets/events/srcs_gt3_spa_3hour_banner.png",
  "event_short_name": "Spa 3H",
  "category": "GT3",
  "event_type": "endurance",
  "series_id": null,
  "venue": "Race Square",
  "track": "Spa-Francorchamps",
  "event_date": "2026-08-16",
  "registration_open": true,
  "registration_type": "multi_route",
  "pricing": {
  "currency": "EUR",
  "standard_driver_entry_fee": 0.0
}
,
  "cars": [
    "GT-M Aero V10 Evo2 – Audi",
    "GT-M Akuro V6 Evo2 – Acura",
    "GT-M Bayer V8 – BMW",
    "GT-M Lanzo V10 Evo2 – Lamborghini",
    "GT-M Lux V8 – Lexus",
    "GT-M Mercer V8 – Mercedes"
  ],
  "public_visible": true,
  "description": "A 3-hour SRCS GT3 endurance event with two drivers per team."
}
